[
  {
    "datasourceId": "global-clipping-osm-land",
    "geo_type": "vector",
    "formats": [
      "subdivided"
    ],
    "classKeys": [],
    "url": "https://d3p1dsef9f0gjr.cloudfront.net/"
  },
  {
    "datasourceId": "global-clipping-eez-land-union",
    "geo_type": "vector",
    "formats": [
      "subdivided"
    ],
    "classKeys": [],
    "url": "https://d3muy0hbwp5qkl.cloudfront.net"
  },
  {
    "datasourceId": "abyssal_classification",
    "geo_type": "vector",
    "keyStats": {
      "Class": {
        "Hills": {
          "count": 69,
          "area": 888456080124.5848
        },
        "Mountains": {
          "count": 58,
          "area": 309591888220.1577
        },
        "Plains": {
          "count": 78,
          "area": 789317620614.2297
        }
      },
      "total": {
        "total": {
          "count": 205,
          "sum": null,
          "area": 1987365588958.9727
        }
      }
    },
    "formats": [
      "fgb"
    ],
    "layerName": "Abyssal_Classification",
    "classKeys": [
      "Class"
    ],
    "created": "2023-06-29T20:22:43.922Z",
    "lastUpdated": "2023-08-08T17:27:10.027Z",
    "src": "data/src/Brazil/Data_Products/geomorphology-clipped-to-eez/Abyssal_Classification.shp",
    "propertiesToKeep": [
      "Class"
    ]
  },
  {
    "datasourceId": "trawling",
    "geo_type": "raster",
    "keyStats": {
      "total": {
        "total": {
          "count": null,
          "sum": 34395232271.26846,
          "area": null
        }
      }
    },
    "formats": [
      "tif"
    ],
    "measurementType": "quantitative",
    "band": 1,
    "noDataValue": 0,
    "created": "2023-07-05T21:31:11.430Z",
    "lastUpdated": "2023-08-08T17:27:17.343Z",
    "src": "data/src/Brazil/Data_Products/south-brazilian-shelf-db/kernel_trawling_preps.tif"
  },
  {
    "datasourceId": "traps",
    "geo_type": "raster",
    "keyStats": {
      "total": {
        "total": {
          "count": null,
          "sum": 101771059.11921157,
          "area": null
        }
      }
    },
    "formats": [
      "tif"
    ],
    "measurementType": "quantitative",
    "band": 1,
    "noDataValue": 0,
    "created": "2023-07-10T20:44:51.499Z",
    "lastUpdated": "2023-08-08T17:27:24.496Z",
    "src": "data/src/Brazil/Data_Products/south-brazilian-shelf-db/kernel_traps_preps.tif"
  },
  {
    "datasourceId": "longline",
    "geo_type": "raster",
    "keyStats": {
      "total": {
        "total": {
          "count": null,
          "sum": 393299687.7165577,
          "area": null
        }
      }
    },
    "formats": [
      "tif"
    ],
    "measurementType": "quantitative",
    "band": 1,
    "noDataValue": 0,
    "created": "2023-07-10T21:09:46.866Z",
    "lastUpdated": "2023-08-08T17:27:31.283Z",
    "src": "data/src/Brazil/Data_Products/south-brazilian-shelf-db/kernel_longline_preps.tif"
  },
  {
    "datasourceId": "gillnet",
    "geo_type": "raster",
    "keyStats": {
      "total": {
        "total": {
          "count": null,
          "sum": 566139222.9722147,
          "area": null
        }
      }
    },
    "formats": [
      "tif"
    ],
    "measurementType": "quantitative",
    "band": 1,
    "noDataValue": 0,
    "created": "2023-07-10T21:10:58.753Z",
    "lastUpdated": "2023-08-08T17:27:38.016Z",
    "src": "data/src/Brazil/Data_Products/south-brazilian-shelf-db/kernel_gillnet_preps.tif"
  },
  {
    "datasourceId": "mining_active",
    "geo_type": "vector",
    "keyStats": {
      "total": {
        "total": {
          "count": 543,
          "sum": null,
          "area": 1245836426.3570294
        }
      }
    },
    "formats": [
      "fgb"
    ],
    "layerName": "mining_active_anm_clipped",
    "classKeys": [],
    "created": "2023-07-11T18:21:33.468Z",
    "lastUpdated": "2023-08-08T17:27:38.305Z",
    "src": "data/src/Brazil/Data_Products/south-brazilian-shelf-db/mining_active_anm_clipped.fgb",
    "propertiesToKeep": []
  },
  {
    "datasourceId": "mining_potential",
    "geo_type": "vector",
    "keyStats": {
      "total": {
        "total": {
          "count": 135,
          "sum": null,
          "area": 365651078733.426
        }
      }
    },
    "formats": [
      "fgb"
    ],
    "layerName": "usos_humanos.mineracao_areas_potenciais",
    "classKeys": [],
    "created": "2023-08-23T18:17:15.043Z",
    "lastUpdated": "2023-08-23T18:17:15.087Z",
    "src": "data/src/fromDatabase/usos_humanos.mineracao_areas_potenciais.json",
    "propertiesToKeep": []
  },
  {
    "datasourceId": "oil_platforms",
    "geo_type": "vector",
    "keyStats": {
      "total": {
        "total": {
          "count": 63,
          "sum": null,
          "area": 0
        }
      }
    },
    "formats": [
      "fgb"
    ],
    "layerName": "usos_humanos.petroleo_plataformas",
    "classKeys": [],
    "created": "2023-08-23T18:17:14.985Z",
    "lastUpdated": "2023-08-23T18:17:14.989Z",
    "src": "data/src/fromDatabase/usos_humanos.petroleo_plataformas.json",
    "propertiesToKeep": []
  },
  {
    "datasourceId": "oil_exploration",
    "geo_type": "vector",
    "keyStats": {
      "total": {
        "total": {
          "count": 27,
          "sum": null,
          "area": 22653113180.664886
        }
      }
    },
    "formats": [
      "fgb"
    ],
    "layerName": "oil_exp_anp",
    "classKeys": [],
    "created": "2023-07-12T20:21:00.643Z",
    "lastUpdated": "2023-08-08T17:42:14.808Z",
    "src": "data/src/Brazil/Data_Products/south-brazilian-shelf-db/oil_exp_anp.fgb",
    "propertiesToKeep": []
  },
  {
    "datasourceId": "ecozones_pelagic",
    "geo_type": "vector",
    "keyStats": {
      "zone": {
        "zone 4": {
          "count": 2,
          "area": 54928779558.6826
        },
        "zone 7": {
          "count": 6,
          "area": 51169900295.240906
        },
        "zone 2": {
          "count": 4,
          "area": 46408591040.50092
        },
        "zone 10": {
          "count": 4,
          "area": 31878296642.02845
        },
        "zone 8": {
          "count": 5,
          "area": 10327776808.869766
        },
        "zone 5": {
          "count": 1,
          "area": 48307094147.54872
        },
        "zone 9": {
          "count": 2,
          "area": 41421505499.52401
        },
        "zone 6": {
          "count": 1,
          "area": 48732980550.91305
        },
        "zone 3": {
          "count": 1,
          "area": 45435367105.853615
        },
        "zone 1": {
          "count": 2,
          "area": 29461332755.951107
        }
      },
      "total": {
        "total": {
          "count": 28,
          "sum": null,
          "area": 408071624405.1132
        }
      }
    },
    "formats": [
      "fgb"
    ],
    "layerName": "ecozones_pelagic_gandra",
    "classKeys": [
      "zone"
    ],
    "created": "2023-07-12T22:06:51.033Z",
    "lastUpdated": "2023-08-08T17:27:39.187Z",
    "src": "data/src/Brazil/Data_Products/south-brazilian-shelf-db/ecozones_pelagic_gandra.fgb",
    "propertiesToKeep": [
      "zone"
    ]
  },
  {
    "datasourceId": "ecozones_benthic",
    "geo_type": "vector",
    "keyStats": {
      "zone": {
        "zone 3": {
          "count": 199,
          "area": 17474132877.81905
        },
        "zone 1": {
          "count": 30,
          "area": 143217044304.99664
        },
        "zone 2": {
          "count": 19,
          "area": 76328672615.80208
        },
        "zone 5": {
          "count": 44,
          "area": 74588670898.60631
        },
        "zone 7": {
          "count": 141,
          "area": 13245555384.885921
        },
        "zone 4": {
          "count": 110,
          "area": 43714294608.70005
        },
        "zone 6": {
          "count": 30,
          "area": 38829211521.04628
        }
      },
      "total": {
        "total": {
          "count": 573,
          "sum": null,
          "area": 407397582211.857
        }
      }
    },
    "formats": [
      "fgb"
    ],
    "layerName": "ecozones_benthic_gandra",
    "classKeys": [
      "zone"
    ],
    "created": "2023-07-12T22:29:40.473Z",
    "lastUpdated": "2023-08-08T17:27:39.647Z",
    "src": "data/src/Brazil/Data_Products/south-brazilian-shelf-db/ecozones_benthic_gandra.fgb",
    "propertiesToKeep": [
      "zone"
    ]
  },
  {
    "datasourceId": "priority_areas",
    "geo_type": "vector",
    "keyStats": {
      "priority": {
        "Extremely High": {
          "count": 220,
          "area": 650169151451.394
        },
        "Very High": {
          "count": 23,
          "area": 210795004379.64093
        },
        "High": {
          "count": 16,
          "area": 376000627093.75806
        },
        "undefined": {
          "count": 1,
          "area": 1990779588083.5898
        }
      },
      "total": {
        "total": {
          "count": 260,
          "sum": null,
          "area": 3227744371008.383
        }
      }
    },
    "formats": [
      "fgb"
    ],
    "layerName": "priority_areas_mma_translated",
    "classKeys": [
      "priority"
    ],
    "created": "2023-07-14T19:10:14.544Z",
    "lastUpdated": "2023-08-08T17:27:40.786Z",
    "src": "data/src/Brazil/Data_Products/south-brazilian-shelf-db/priority_areas_mma_translated.fgb",
    "propertiesToKeep": [
      "priority"
    ]
  },
  {
    "datasourceId": "oil_gas_exploration",
    "geo_type": "vector",
    "keyStats": {
      "total": {
        "total": {
          "count": 27,
          "sum": null,
          "area": 22653113180.664886
        }
      }
    },
    "formats": [
      "fgb"
    ],
    "layerName": "oil_exp_anp",
    "classKeys": [],
    "created": "2023-07-17T18:40:51.731Z",
    "lastUpdated": "2023-08-08T17:27:41.011Z",
    "src": "data/src/Brazil/Data_Products/south-brazilian-shelf-db/oil_exp_anp.fgb",
    "propertiesToKeep": []
  },
  {
    "datasourceId": "shipping_intensity",
    "geo_type": "vector",
    "keyStats": {
      "intensity": {
        "Low": {
          "count": 1944,
          "area": 280878500879.52954
        },
        "Medium": {
          "count": 3149,
          "area": 47695315451.504616
        },
        "High": {
          "count": 1407,
          "area": 113902892619.22852
        },
        "undefined": {
          "count": 401,
          "area": 137135903518.0804
        }
      },
      "total": {
        "total": {
          "count": 6901,
          "sum": null,
          "area": 579612612468.3446
        }
      }
    },
    "formats": [
      "fgb"
    ],
    "layerName": "shipping_intensity_clipped",
    "classKeys": [
      "intensity"
    ],
    "created": "2023-07-21T20:38:02.142Z",
    "lastUpdated": "2023-08-08T17:27:43.741Z",
    "src": "data/src/Brazil/Data_Products/south-brazilian-shelf-db/shipping_intensity_clipped.fgb",
    "propertiesToKeep": [
      "intensity"
    ]
  },
  {
    "datasourceId": "mining_active_central-east",
    "geo_type": "vector",
    "keyStats": {
      "total": {
        "total": {
          "count": 164,
          "sum": null,
          "area": 539055700.3251766
        }
      }
    },
    "formats": [
      "fgb"
    ],
    "layerName": "mining_active_central-east",
    "classKeys": [],
    "created": "2023-07-26T23:32:56.477Z",
    "lastUpdated": "2023-08-08T17:27:44.007Z",
    "src": "data/src/Brazil/Data_Products/region-test/mining_active_central-east.fgb",
    "propertiesToKeep": []
  },
  {
    "datasourceId": "mining_active_south",
    "geo_type": "vector",
    "keyStats": {
      "total": {
        "total": {
          "count": 368,
          "sum": null,
          "area": 696540431.481384
        }
      }
    },
    "formats": [
      "fgb"
    ],
    "layerName": "mining_active_south",
    "classKeys": [],
    "created": "2023-07-26T23:33:34.870Z",
    "lastUpdated": "2023-08-08T17:27:44.248Z",
    "src": "data/src/Brazil/Data_Products/region-test/mining_active_south.fgb",
    "propertiesToKeep": []
  },
  {
    "datasourceId": "mining_potential_central-east",
    "geo_type": "vector",
    "keyStats": {
      "total": {
        "total": {
          "count": 28,
          "sum": null,
          "area": 61474305634.50131
        }
      }
    },
    "formats": [
      "fgb"
    ],
    "layerName": "mining_potential_central-east",
    "classKeys": [],
    "created": "2023-07-26T23:34:34.387Z",
    "lastUpdated": "2023-08-08T17:27:44.533Z",
    "src": "data/src/Brazil/Data_Products/region-test/mining_potential_central-east.fgb",
    "propertiesToKeep": []
  },
  {
    "datasourceId": "mining_potential_north",
    "geo_type": "vector",
    "keyStats": {
      "total": {
        "total": {
          "count": 15,
          "sum": null,
          "area": 65155946688.930725
        }
      }
    },
    "formats": [
      "fgb"
    ],
    "layerName": "mining_potential_north",
    "classKeys": [],
    "created": "2023-07-26T23:35:12.032Z",
    "lastUpdated": "2023-08-08T17:27:44.784Z",
    "src": "data/src/Brazil/Data_Products/region-test/mining_potential_north.fgb",
    "propertiesToKeep": []
  },
  {
    "datasourceId": "mining_potential_northeast",
    "geo_type": "vector",
    "keyStats": {
      "total": {
        "total": {
          "count": 86,
          "sum": null,
          "area": 98479921048.17107
        }
      }
    },
    "formats": [
      "fgb"
    ],
    "layerName": "mining_potential_northeast",
    "classKeys": [],
    "created": "2023-07-26T23:35:44.679Z",
    "lastUpdated": "2023-08-08T17:27:45.049Z",
    "src": "data/src/Brazil/Data_Products/region-test/mining_potential_northeast.fgb",
    "propertiesToKeep": []
  },
  {
    "datasourceId": "mining_potential_south",
    "geo_type": "vector",
    "keyStats": {
      "total": {
        "total": {
          "count": 35,
          "sum": null,
          "area": 42303438767.39601
        }
      }
    },
    "formats": [
      "fgb"
    ],
    "layerName": "mining_potential_south",
    "classKeys": [],
    "created": "2023-07-26T23:36:42.040Z",
    "lastUpdated": "2023-08-08T17:27:45.285Z",
    "src": "data/src/Brazil/Data_Products/region-test/mining_potential_south.fgb",
    "propertiesToKeep": []
  },
  {
    "datasourceId": "wind_farms",
    "geo_type": "vector",
    "keyStats": {
      "total": {
        "total": {
          "count": 81,
          "sum": null,
          "area": 53449119379.33059
        }
      }
    },
    "formats": [
      "fgb"
    ],
    "layerName": "usos_humanos.eolico_parques",
    "classKeys": [],
    "created": "2023-08-23T18:17:14.693Z",
    "lastUpdated": "2023-08-23T18:17:14.733Z",
    "src": "data/src/fromDatabase/usos_humanos.eolico_parques.json",
    "propertiesToKeep": []
  },
  {
    "datasourceId": "wind_towers",
    "geo_type": "vector",
    "keyStats": {
      "total": {
        "total": {
          "count": 12784,
          "sum": null,
          "area": 0
        }
      }
    },
    "formats": [
      "fgb"
    ],
    "layerName": "usos_humanos.eolico_torres",
    "classKeys": [],
    "created": "2023-08-23T18:17:20.338Z",
    "lastUpdated": "2023-08-23T18:17:20.340Z",
    "src": "data/src/fromDatabase/usos_humanos.eolico_torres.json",
    "propertiesToKeep": []
  },
  {
    "datasourceId": "power_lines",
    "geo_type": "vector",
    "keyStats": {
      "total": {
        "total": {
          "count": 2450,
          "sum": null,
          "area": 0
        }
      }
    },
    "formats": [
      "fgb"
    ],
    "layerName": "usos_humanos.eolico_linhas_transmissao",
    "classKeys": [],
    "created": "2023-08-23T18:17:17.997Z",
    "lastUpdated": "2023-08-23T18:17:18.000Z",
    "src": "data/src/fromDatabase/usos_humanos.eolico_linhas_transmissao.json",
    "propertiesToKeep": []
  },
  {
    "datasourceId": "bathymetric_classes",
    "geo_type": "vector",
    "keyStats": {
      "class": {
        "Plataforma Externa Rasa (50 - 100 m)": {
          "count": 408,
          "area": 195473959993.6156
        },
        "Plataforma Interna (<50 m)": {
          "count": 221,
          "area": 392729041241.2966
        },
        "Plataforma Externa Profunda (100 - 200 m)": {
          "count": 748,
          "area": 117619623384.75525
        },
        "Talude (200 - 1200 m )": {
          "count": 61,
          "area": 184372460414.18106
        },
        "Bacia Oceânica (> 1200 m)": {
          "count": 4,
          "area": 4865824872637.069
        }
      },
      "total": {
        "total": {
          "count": 1442,
          "sum": null,
          "area": 5756019957670.928
        }
      }
    },
    "formats": [
      "fgb"
    ],
    "layerName": "batimetria_classes",
    "classKeys": [
      "class"
    ],
    "created": "2023-08-23T18:17:18.797Z",
    "lastUpdated": "2023-08-23T18:17:18.799Z",
    "src": "data/src/fromDatabase/public.batimetria_classes.json",
    "propertiesToKeep": [
      "class"
    ]
  },
  {
    "datasourceId": "mining_process",
    "geo_type": "vector",
    "keyStats": {
      "total": {
        "total": {
          "count": 821,
          "sum": null,
          "area": 14745682385.508148
        }
      }
    },
    "formats": [
      "fgb"
    ],
    "layerName": "usos_humanos.mineracao_processos",
    "classKeys": [],
    "created": "2023-08-23T18:17:15.344Z",
    "lastUpdated": "2023-08-23T18:17:15.347Z",
    "src": "data/src/fromDatabase/usos_humanos.mineracao_processos.json",
    "propertiesToKeep": []
  },
  {
    "datasourceId": "oil_blocks_concession",
    "geo_type": "vector",
    "keyStats": {
      "total": {
        "total": {
          "count": 123,
          "sum": null,
          "area": 91968171767.41112
        }
      }
    },
    "formats": [
      "fgb"
    ],
    "layerName": "usos_humanos.petroleo_blocos_concessao",
    "classKeys": [],
    "created": "2023-08-23T18:17:15.234Z",
    "lastUpdated": "2023-08-23T18:17:15.238Z",
    "src": "data/src/fromDatabase/usos_humanos.petroleo_blocos_concessao.json",
    "propertiesToKeep": []
  },
  {
    "datasourceId": "oil_production_fields",
    "geo_type": "vector",
    "keyStats": {
      "total": {
        "total": {
          "count": 150,
          "sum": null,
          "area": 23608185910.286736
        }
      }
    },
    "formats": [
      "fgb"
    ],
    "layerName": "usos_humanos.petroleo_campos_producao",
    "classKeys": [],
    "created": "2023-08-23T18:17:15.481Z",
    "lastUpdated": "2023-08-23T18:17:15.487Z",
    "src": "data/src/fromDatabase/usos_humanos.petroleo_campos_producao.json",
    "propertiesToKeep": []
  },
  {
    "src": "data/src/fromDatabase/usos_humanos.portos.json",
    "layerName": "usos_humanos.portos",
    "geo_type": "vector",
    "datasourceId": "ports",
    "formats": [
      "fgb"
    ],
    "classKeys": [],
    "created": "2023-08-23T18:22:30.972Z",
    "lastUpdated": "2023-08-23T18:22:30.972Z",
    "keyStats": {
      "total": {
        "total": {
          "count": 122,
          "sum": null,
          "area": 0
        }
      }
    },
    "propertiesToKeep": []
  }
]