[
  {
    "metricId": "boundaryAreaOverlap",
    "type": "areaOverlap",
    "classes": [
      {
        "classId": "eez",
        "display": "EEZ",
        "datasourceId": "global-clipping-eez-land-union",
        "objectiveId": "eez",
        "layerId": ""
      }
    ]
  },
  {
    "metricId": "geomorphicOverlap",
    "type": "areaOverlap",
    "classes": [
      {
        "classId": "Hills",
        "classKey": "Class",
        "display": "Abyssal Hill",
        "datasourceId": "abyssal_classification",
        "objectiveId": "eez",
        "layerId": ""
      },
      {
        "classId": "Mountains",
        "classKey": "Class",
        "display": "Abyssal Mountain",
        "datasourceId": "abyssal_classification",
        "objectiveId": "eez",
        "layerId": ""
      },
      {
        "classId": "Plains",
        "classKey": "Class",
        "display": "Abyssal Plain",
        "datasourceId": "abyssal_classification",
        "objectiveId": "eez",
        "layerId": ""
      }
    ]
  },
  {
    "metricId": "priorityAreaOverlap",
    "type": "areaOverlap",
    "layerId": "Gx38O_Msj",
    "classes": [
      {
        "classId": "High",
        "classKey": "priority",
        "display": "High",
        "datasourceId": "priority_areas",
        "objectiveId": "eez",
        "layerId": "Gx38O_Msj"
      },
      {
        "classId": "Very High",
        "classKey": "priority",
        "display": "Very High",
        "datasourceId": "priority_areas",
        "objectiveId": "eez",
        "layerId": "Gx38O_Msj"
      },
      {
        "classId": "Extremely High",
        "classKey": "priority",
        "display": "Extremely High",
        "datasourceId": "priority_areas",
        "objectiveId": "eez",
        "layerId": "Gx38O_Msj"
      }
    ]
  },
  {
    "metricId": "fishingEffortOverlap",
    "type": "valueOverlap",
    "classes": [
      {
        "classId": "trawling",
        "display": "Trawling",
        "datasourceId": "trawling",
        "noDataValue": 0,
        "layerId": "nVmRI8vJX"
      },
      {
        "classId": "traps",
        "display": "Traps",
        "datasourceId": "traps",
        "noDataValue": 0,
        "layerId": ""
      },
      {
        "classId": "longline",
        "display": "Longline",
        "datasourceId": "longline",
        "noDataValue": 0,
        "layerId": "Olt_SOCh0"
      },
      {
        "classId": "gillnet",
        "display": "Gillnet",
        "datasourceId": "gillnet",
        "noDataValue": 0,
        "layerId": "awuKJnhRG"
      }
    ]
  },
  {
    "metricId": "miningOverlap",
    "type": "areaOverlap",
    "classes": [
      {
        "classId": "mining_active_all",
        "display": "Active Mining",
        "datasourceId": "mining_active",
        "layerId": "rmz5haLwD"
      },
      {
        "classId": "mining_potential_all",
        "display": "Potential Mining",
        "datasourceId": "mining_potential",
        "layerId": "HhykfJ_h9"
      },
      {
        "classId": "mining_active_central-east",
        "display": "Active Mining",
        "datasourceId": "mining_active_central-east",
        "layerId": "rmz5haLwD"
      },
      {
        "classId": "mining_active_south",
        "display": "Active Mining",
        "datasourceId": "mining_active_south",
        "layerId": "rmz5haLwD"
      },
      {
        "classId": "mining_potential_central-east",
        "display": "Potential Mining",
        "datasourceId": "mining_potential_central-east",
        "layerId": "HhykfJ_h9"
      },
      {
        "classId": "mining_potential_north",
        "display": "Potential Mining",
        "datasourceId": "mining_potential_north",
        "layerId": "HhykfJ_h9"
      },
      {
        "classId": "mining_potential_northeast",
        "display": "Potential Mining",
        "datasourceId": "mining_potential_northeast",
        "layerId": "HhykfJ_h9"
      },
      {
        "classId": "mining_potential_south",
        "display": "Potential Mining",
        "datasourceId": "mining_potential_south",
        "layerId": "HhykfJ_h9"
      }
    ]
  },
  {
    "metricId": "shippingOverlap",
    "type": "areaOverlap",
    "layerId": "ohTda51j7",
    "classes": [
      {
        "classId": "Low",
        "classKey": "intensity",
        "display": "Low",
        "datasourceId": "shipping_intensity",
        "objectiveId": ""
      },
      {
        "classId": "Medium",
        "classKey": "intensity",
        "display": "Medium",
        "datasourceId": "shipping_intensity",
        "objectiveId": ""
      },
      {
        "classId": "High",
        "classKey": "intensity",
        "display": "High",
        "datasourceId": "shipping_intensity",
        "objectiveId": ""
      }
    ]
  },
  {
    "metricId": "ecozonesPelagicOverlap",
    "type": "areaOverlap",
    "layerId": "Qaj5XRtiU",
    "classes": [
      {
        "classId": "zone 1",
        "classKey": "zone",
        "display": "1",
        "datasourceId": "ecozones_pelagic",
        "objectiveId": "",
        "layerId": ""
      },
      {
        "classId": "zone 2",
        "classKey": "zone",
        "display": "2",
        "datasourceId": "ecozones_pelagic",
        "objectiveId": "",
        "layerId": ""
      },
      {
        "classId": "zone 3",
        "classKey": "zone",
        "display": "3",
        "datasourceId": "ecozones_pelagic",
        "objectiveId": "",
        "layerId": ""
      },
      {
        "classId": "zone 4",
        "classKey": "zone",
        "display": "4",
        "datasourceId": "ecozones_pelagic",
        "objectiveId": "",
        "layerId": ""
      },
      {
        "classId": "zone 5",
        "classKey": "zone",
        "display": "5",
        "datasourceId": "ecozones_pelagic",
        "objectiveId": "",
        "layerId": ""
      },
      {
        "classId": "zone 6",
        "classKey": "zone",
        "display": "6",
        "datasourceId": "ecozones_pelagic",
        "objectiveId": "",
        "layerId": ""
      },
      {
        "classId": "zone 7",
        "classKey": "zone",
        "display": "7",
        "datasourceId": "ecozones_pelagic",
        "objectiveId": "",
        "layerId": ""
      },
      {
        "classId": "zone 8",
        "classKey": "zone",
        "display": "8",
        "datasourceId": "ecozones_pelagic",
        "objectiveId": "",
        "layerId": ""
      },
      {
        "classId": "zone 9",
        "classKey": "zone",
        "display": "9",
        "datasourceId": "ecozones_pelagic",
        "objectiveId": "",
        "layerId": ""
      },
      {
        "classId": "zone 10",
        "classKey": "zone",
        "display": "10",
        "datasourceId": "ecozones_pelagic",
        "objectiveId": "",
        "layerId": ""
      }
    ]
  },
  {
    "metricId": "ecozonesBenthicOverlap",
    "type": "areaOverlap",
    "layerId": "UmN9AuWc2",
    "classes": [
      {
        "classId": "zone 1",
        "classKey": "zone",
        "display": "1",
        "datasourceId": "ecozones_benthic",
        "objectiveId": "",
        "layerId": ""
      },
      {
        "classId": "zone 2",
        "classKey": "zone",
        "display": "2",
        "datasourceId": "ecozones_benthic",
        "objectiveId": "",
        "layerId": ""
      },
      {
        "classId": "zone 3",
        "classKey": "zone",
        "display": "3",
        "datasourceId": "ecozones_benthic",
        "objectiveId": "",
        "layerId": ""
      },
      {
        "classId": "zone 4",
        "classKey": "zone",
        "display": "4",
        "datasourceId": "ecozones_benthic",
        "objectiveId": "",
        "layerId": ""
      },
      {
        "classId": "zone 5",
        "classKey": "zone",
        "display": "5",
        "datasourceId": "ecozones_benthic",
        "objectiveId": "",
        "layerId": ""
      },
      {
        "classId": "zone 6",
        "classKey": "zone",
        "display": "6",
        "datasourceId": "ecozones_benthic",
        "objectiveId": "",
        "layerId": ""
      },
      {
        "classId": "zone 7",
        "classKey": "zone",
        "display": "7",
        "datasourceId": "ecozones_benthic",
        "objectiveId": "",
        "layerId": ""
      }
    ]
  },
  {
    "metricId": "oilExplorationOverlap",
    "type": "areaOverlap",
    "classes": [
      {
        "classId": "oil_gas_exploration",
        "display": "Oil and Gas Exploration",
        "datasourceId": "oil_gas_exploration",
        "layerId": "ElSJFfo1x"
      }
    ]
  }
]
